{"0": ["lauris", "reiniks", "takes", "hollywood", "sign", "los", "angeles", "showing", "way", "get", "sharing", "useful", "advice", "best", "way", "see", "hollywood", "sign", "drive", "beachwood", "drive", "north", "hollywood", "boulevard", "keep", "left", "fork", "intersection", "go", "way", "sunset", "ranch", "way", "sign", "polite", "loud", "drive", "fast"], "1": ["entry", "posted", "advertising", "building", "traveling", "walking", "tagged", "hollywood", "sign", "get", "hollywood", "sign", "best", "place", "see", "hollywood", "sign", "best", "way", "see", "hollywood", "sign", "bookmark", "permalink"], "2": ["best", "way", "see", "hollywood", "sign", "drive", "beachwood", "drive", "north", "hollywood", "boulevard", "sign", "clearly", "visible", "way", "beachwood", "although", "hills", "begin", "obscure", "view", "sign", "near", "top", "drive"], "3": ["canyon", "lake", "drive", "best", "place", "see", "hollywood", "sign", "exact", "street", "address", "location", "canyon", "lake", "drive", "hollywood", "enter", "address", "google", "maps", "get", "driving", "directions", "easiest", "way", "get", "take", "us", "exit", "barham", "blvd"], "4": ["going", "send", "land", "go", "away", "tourists", "whatever", "means", "honesty", "best", "place", "see", "sign", "want", "get", "even", "closer", "best", "place", "near", "lake", "hollywood", "park", "located", "canyon", "lake", "drive", "los", "angeles", "ca"], "5": ["see", "hollywood", "sign", "see", "hollywood", "sign", "many", "places", "around", "los", "angeles", "quick", "drive", "mulholland", "drive", "hollywood", "reservoir", "reward", "glimpse", "living", "hollywood", "hills", "great", "city", "views"]}