{"0": ["total", "costs", "do-it-yourself", "brick", "patio", "run", "2.80", "square", "foot", "10x20", "foot", "area", "according", "askthebuilder.com", "brick", "patio", "professionally", "installed", "run", "around", "square", "foot", "labor", "materials", "3,000", "10x20", "foot", "area", "according", "landscape-design-advice.com"], "1": ["average", "cost", "cubic", "yard", "concrete", "depending", "much", "needed", "local", "prices", "labor", "costs", "pour", "form", "concrete", "run", "somewhere", "around", "3.50", "7.00", "per", "square", "foot", "one", "homeowner", "paid", "11,000", "crawl", "space", "1,500", "square", "foot", "home", "concrete", "prices", "help", "determine", "new", "concrete", "foundation", "cost", "concrete", "typically", "measured", "cubic", "yards", "x3", "x3"], "2": ["concrete", "typically", "measured", "cubic", "yards", "x3", "x3", "average", "cost", "cubic", "yard", "concrete", "depending", "much", "needed", "local", "prices", "labor", "costs", "pour", "form", "concrete", "run", "somewhere", "around", "3.50", "7.00", "per", "square", "foot", "concrete", "prices", "help", "determine", "new", "concrete", "foundation", "cost"], "3": ["get", "instant", "estimate", "cost", "install", "cement", "slab", "free", "calculator", "uses", "recent", "trusted", "data", "estimate", "costs", "cement", "slab", "installation", "project", "basic", "square", "feet", "project", "zip", "code", "benchmark", "cost", "install", "cement", "slab", "ranges", "4.50", "6.30", "per", "square", "foot", "estimate", "costs", "project", "set", "project", "zip", "code", "enter", "zip", "code", "location", "labor", "hired", "materials", "purchased"], "4": ["video", "cost", "concrete", "floors", "depending", "level", "complexity", "concrete", "floors", "cost", "little", "square", "foot", "expensive", "square", "foot"], "5": ["cost", "factors", "involved", "installing", "tile", "concrete", "flooring", "additional", "labor", "hours", "materials", "needed", "smooth", "level", "floor", "surface", "preparation", "laying", "tile", "cement", "floor", "tile", "installer", "must", "ensure", "floor", "clean", "smooth", "dry", "free", "holes", "divots"], "6": ["site", "might", "help", "average", "cost", "labor", "materials", "pouring", "concrete", "need", "4.75", "yards", "concrete", "poured", "small", "parking", "pad", "patio", "addition", "sidewalk", "widen", "best", "answer", "yard", "concrete", "cover", "square", "feet", "poured", "inches", "thick", "square", "feet", "4.73", "square", "foot"], "7": ["get", "instant", "estimate", "cost", "install", "concrete", "pad", "free", "calculator", "uses", "recent", "trusted", "data", "estimate", "costs", "concrete", "pad", "installation", "project", "basic", "square", "feet", "project", "zip", "code", "benchmark", "cost", "install", "concrete", "pad", "ranges", "4.64", "6.36", "per", "square", "foot", "estimate", "costs", "project", "set", "project", "zip", "code", "enter", "zip", "code", "location", "labor", "hired", "materials", "purchased"], "8": ["labor", "costs", "pour", "form", "concrete", "run", "somewhere", "around", "3.50", "7.00", "per", "square", "foot", "one", "homeowner", "paid", "11,000", "crawl", "space", "1,500", "square", "foot", "home", "one", "customer", "texas", "received", "quote", "2,500", "square", "foot", "foundation", "slab", "20,000", "concrete", "prices", "help", "determine", "new", "concrete", "foundation", "cost", "concrete", "typically", "measured", "cubic", "yards", "x3", "x3", "average", "cost", "cubic", "yard", "concrete", "depending", "much", "needed", "local", "prices"], "9": ["basic", "concrete", "slab", "cost", "i'll", "base", "price", "actual", "estimate", "would", "install", "thick", "concrete", "slab", "one", "customers", "base", "cost", "thick", "concrete", "slab", "4.00", "dollars", "per", "square", "foot", "take", "length", "concrete", "slab", "x", "width", "slab", "get", "total", "square", "footage", "multiply", "total", "square", "footage", "dollars", "get", "total", "price"]}