{"0": ["fail", "appear", "ordered", "court", "warrant", "may", "issued", "arrest", "additionally", "actions", "may", "also", "take", "place", "result", "failure", "appear", "comply", "court", "order", "ordering", "issuance", "warrant", "arrest", "holding", "warrant", "future", "hearing", "date"], "1": ["means", "warrant", "arrest", "outstanding", "pulled", "police", "officer", "may", "arrest", "take", "jail", "appear", "court", "addition", "civil", "assessment", "fine", "referral", "matter", "court's", "collection", "vendor", "even", "receive", "court's", "courtesy", "notice", "responsible", "appearing", "date", "fail", "appear", "date", "ticket", "extension", "date", "granted", "date", "scheduled", "appear", "court", "court", "take", "several", "actions"], "2": ["court", "issue", "fta", "failure", "appear", "charge", "arrest", "warrant", "fail", "appear", "court", "court", "date", "fail", "pay", "speeding", "ticket", "fine", "many", "courts", "issue", "fta", "failure", "appear", "charge", "miss", "first", "court", "date", "miss", "court", "second", "time", "court", "issue", "arrest", "warrant", "set", "bond", "amount", "money", "pay", "court", "get", "warrant", "cancelled", "get", "new", "court", "date"], "3": ["juror", "late", "juror", "receive", "failure", "appear", "summons", "appear", "jury", "duty", "different", "day", "days", "jurors", "plan", "arrive", "garage", "least", "minutes", "prior", "check-in", "time", "selected", "serve", "jury", "trial", "service", "complete", "conclusion", "trial", "average", "trial", "lasts", "three", "five", "days", "municipal", "courts", "justice", "peace", "courts", "use", "pooling", "system", "means", "call", "court", "period", "time", "weeks"], "4": ["please", "call", "(800) 927-0644", "missing", "court", "date", "like", "missing", "appointment", "facing", "criminal", "charges", "failure", "appear", "need", "aggressive", "determined", "defense", "attorney", "side", "miss", "criminal", "court", "date", "considered", "fugitive", "cases", "bench", "warrant", "issued", "arrest", "failure", "appear", "court", "serious", "usually", "options", "fix", "problem", "missed", "court", "date", "legitimate", "reason", "mistake", "even", "moment", "panic", "help", "critical", "right", "away"], "5": ["request", "postponement", "follow", "instructions", "juror", "affidavit", "questionnaire", "summons", "contact", "court", "scheduled", "appear", "inconvenience", "prospective", "trial", "juror", "employer", "legal", "reason", "excused", "jury", "service", "since", "evidence", "consider", "presented", "court", "allowed", "make", "independent", "investigation", "visit", "places", "involved", "case", "necessary", "jury", "visit", "site", "judge", "order", "send", "jury", "group", "see", "control", "emotions"], "6": ["addition", "failure", "appear", "charge", "bail", "forfeited", "bond", "time", "failure", "appear", "simply", "means", "money", "posted", "release", "lost", "facing", "additional", "charges", "probably", "mind", "missed", "court", "date", "call", "us", "today", "discuss", "failure", "appear", "case", "warrant", "help", "decide", "next", "move", "get", "place", "make", "things", "right"], "7": ["failed", "appear", "district", "court", "date", "time", "location", "provided", "summons", "arraignment", "court", "sent", "court", "likely", "entered", "default", "issued", "warrant", "arrest", "means", "may", "outstanding", "warrant", "arrest", "believe", "qualify", "jury", "duty", "bring", "proof", "disqualification", "court", "requesting", "removal", "default", "recall", "warrant", "also", "send", "copy", "proof", "disqualification", "office", "jury", "commissioner"], "8": ["served", "jury", "panel", "trial", "exempt", "serving", "two", "years", "months", "two", "years", "since", "last", "service", "required", "appear", "jury", "service", "regardless", "many", "times", "served", "past", "selected", "serve", "jury", "trial", "service", "complete", "conclusion", "trial", "average", "trial", "lasts", "three", "five", "days", "municipal", "courts", "justice", "peace", "courts", "use", "pooling", "system", "means", "call", "court", "period", "time", "weeks"], "9": ["continue", "reading", "find", "happens", "ignore", "jury", "summons", "failure", "appear", "jury", "duty", "cases", "one", "person", "likely", "ignore", "another", "jury", "summons", "jermaine", "dupri", "ceo", "def", "recordings", "dupri", "recently", "served", "three-day", "jail", "sentence", "fayetteville", "georgia", "missing", "jury", "duty", "march", "consequences", "ignoring", "jury", "summons", "ignore", "jury", "summons", "phoenix", "arizona", "sheriff's", "deputy", "might", "show", "door", "many", "jurisdictions", "bench", "warrants", "issued", "failing", "appear", "could", "lead", "arrests", "routine", "traffic", "stops"]}