{"0": ["printer-friendly", "version", "according", "boarding", "school", "review", "average", "boarding", "school", "tuition", "u", "citizen", "46,750", "per", "year", "today", "10/29", "tuition", "ranges", "incredibly", "vast", "mere", "2,000", "per", "year", "86,000", "per", "year--although", "first", "five", "schools", "10,000", "35,000", "per", "year"], "1": ["residential", "boarding", "high", "school", "cost", "30,000-", "80,000", "year", "members", "national", "association", "independent", "schools", "charge", "average", "median", "45,219", "boarding", "school", "costs", "46,000", "chapel", "hill-chauncy", "hall", "school", "waltham", "53,925", "woodside", "priory", "school", "portola", "valley", "ca", "public", "schools", "charge", "per", "year", "on-campus", "student", "parking", "south", "high", "school", "newton", "annual", "student", "parking", "fee", "parent", "may", "responsible", "providing", "transportation", "private", "school", "cost", "2,000"], "2": ["making", "world", "better", "one", "answer", "time", "annual", "tuition", "rates", "private", "american", "boarding", "high", "schools", "range", "7,332", "45,000", "average", "annual", "tuition", "boarding", "student", "31,416", "source", "college", "board's", "trends", "college", "pricing"], "3": ["according", "collegebound.net", "average", "boarding", "school", "vary", "price", "anywhere", "10,000", "60,000", "noted", "average", "boarding", "school", "tuition", "today", "around", "38,850", "boarding", "schools", "going", "widely", "vary", "anywhere", "1,000", "students", "average", "school", "though", "around", "classmates", "boarding", "schools", "widely", "vary", "regarding", "going", "teach", "curriculum", "use"], "4": ["members", "national", "association", "independent", "schools", "charge", "average", "median", "45,219", "boarding", "school", "costs", "46,000", "chapel", "hill-chauncy", "hall", "school", "waltham", "53,925", "woodside", "priory", "school", "portola", "valley", "ca", "public", "schools", "charge", "per", "year", "on-campus", "student", "parking", "south", "high", "school", "newton", "annual", "student", "parking", "fee", "parent", "may", "responsible", "providing", "transportation", "private", "school", "cost", "2,000"], "5": ["average", "annual", "boarding", "school", "tuition", "38,850", "course", "schools", "tuition", "low", "10,000", "others", "high", "60,000", "georgia", "residents", "pay", "5,500", "out-of-state", "students", "pay", "10,050", "still", "much", "lower", "average", "cost", "boarding", "school"], "6": ["considering", "therapeutic", "boarding", "schools", "however", "expect", "pay", "lot", "would", "traditional", "boarding", "school", "special", "services", "provided", "therapeutic", "boarding", "schools", "tuition", "ranges", "around", "3,500", "7,500", "per", "month", "42,000", "90,000", "per", "year", "georgia", "residents", "pay", "5,500", "out-of-state", "students", "pay", "10,050", "still", "much", "lower", "average", "cost"], "7": ["boarding", "schools", "offer", "special", "services", "clinical", "sessions", "cost", "compared", "typical", "boarding", "school", "tuition", "rates", "special", "services", "tuition", "high", "7,000", "per", "year", "depending", "child", "disability", "staying", "campus", "often", "cost", "5,000", "10,000", "per", "year", "boarding", "schools", "going", "widely", "vary", "anywhere", "1,000", "students", "average", "school", "though", "around", "classmates", "boarding", "schools", "widely", "vary", "regarding", "going", "teach", "curriculum", "use"], "8": ["average", "boarding", "school", "financial", "aid", "grant", "17,000", "percent", "students", "financial", "aid", "boarding", "schools", "offer", "higher", "percentage", "financial", "aid", "grants", "others", "greatly", "increases", "affordability", "georgia", "residents", "pay", "5,500", "out-of-state", "students", "pay", "10,050", "still", "much", "lower", "average", "cost", "boarding", "school"], "9": ["state-supported", "boarding", "schools", "advanced", "academy", "georgia", "carrollton", "ga", "in-state", "students", "benefit", "reduced", "tuition", "georgia", "residents", "pay", "5,500", "out-of-state", "students", "pay", "10,050", "still", "much", "lower", "average", "cost", "boarding", "school"]}