{"0": ["people", "think", "patrick", "swayze", "movie", "dirty", "dancing", "ghost", "pops", "mind", "patrick", "born", "houston", "texas", "jesse", "wayne", "patsy", "yvonne", "swayze"], "1": ["patrick", "swayze", "patrick", "wayne", "swayze", "born", "aug", "houston", "tx", "father", "jesse", "wayne", "champion", "rodeo", "cowboy", "mom", "patsy", "yvonne", "swayze", "dancer", "choreographer", "owned", "houston", "jazz", "ballet", "company"], "2": ["birth", "name", "patrick", "wayne", "swayze", "biography", "athlete", "practically", "birth", "patrick", "swayze", "football", "player", "high", "school", "earned", "gymnastics", "scholarship", "pay", "college", "father", "dancer", "choreographer", "swayze", "began", "study", "dance", "early", "eventually", "continued"], "3": ["official", "photos", "\u00bb", "patrick", "wayne", "swayze", "born", "august", "houston", "texas", "patsy", "yvonne", "helen", "karnes", "jesse", "wayne", "swayze", "chemical", "plant", "engineer", "draftsman", "mother", "choreographer", "patsy", "swayze", "owned", "dance", "school", "houston", "patrick", "also", "student"], "4": ["athlete", "practically", "birth", "patrick", "swayze", "football", "player", "high", "school", "earned", "gymnastics", "scholarship", "pay", "college", "father", "dancer", "choreographer", "swayze", "began", "study", "dance", "early", "eventually", "working", "prestigious", "harkness", "\u2026"], "5": ["biography", "athlete", "practically", "birth", "patrick", "swayze", "football", "player", "high", "school", "earned", "gymnastics", "scholarship", "pay", "college", "father", "dancer", "choreographer", "swayze", "began", "study", "dance", "early", "eventually", "continued"], "6": ["actor", "dancer", "singer", "patrick", "swayze", "texas-born", "movie", "actor", "whose", "background", "ballet", "gymnastics", "ironically", "gave", "physique", "well-suited", "roles", "hunky", "love", "interest", "macho", "action", "film", "hero", "early", "roles"]}