{"0": ["bloating", "fullness", "distended", "stomach", "weight", "gain", "webmd", "symptom", "checker", "helps", "find", "common", "medical", "conditions", "indicated", "symptoms", "bloating", "fullness", "distended", "stomach", "weight", "gain", "including", "gas", "pains", "irritable", "bowel", "syndrome", "congestive", "heart", "failure"], "1": ["abdominal", "bloating", "constipation", "cause", "sick", "fat", "slowing", "metabolism", "causing", "weight", "gain", "establishing", "hormonal", "imbalances", "first", "step", "finding", "cure", "abdominal", "bloating", "irritable", "bowel", "syndrome", "hypothyroidism", "pms", "poly", "cystic", "ovarian", "disorder", "menopause", "fibroids", "cysts", "endometriosis"], "2": ["causes", "bloating", "weight", "gain", "treatment", "suffer", "chronic", "bloating", "accompanied", "symptoms", "like", "weight", "gain", "consult", "doctor", "immediately", "mentioned", "causes", "symptoms", "treated", "medications", "making", "changes", "lifestyle", "causes", "lot", "discomfort", "also", "makes", "person", "irritable", "common", "symptom", "conditions", "like", "irritable", "bowel", "syndrome", "constipation", "etc", "however", "bloated", "stomach", "weight", "gain", "together", "rare", "symptom", "observed", "case", "certain", "health", "conditions"], "3": ["cushing's", "syndrome", "weight", "gain", "common", "symptom", "cushing's", "syndrome", "condition", "exposed", "much", "stress", "hormone", "cortisol", "turn", "causes", "weight", "gain", "abnormalities", "get", "cushing's", "syndrome", "take", "steroids", "asthma", "arthritis", "lupus", "anti-inflammatory", "steroid", "medications", "like", "prednisone", "notorious", "causing", "weight", "gain", "fluid", "retention", "increased", "appetite", "main", "reasons", "people", "may", "also", "see", "temporary", "change", "body", "holds", "fat", "taking", "steroids", "places", "like", "face", "belly", "back", "neck"], "4": ["alone.difficult", "weight", "gain", "stomach", "belly", "waist", "hips", "thighs", "nearly", "impossible", "lose", "unless", "properly", "identify", "underlying", "factor", "causing", "weight", "gain", "always", "easy", "many", "potential", "causes", "weight", "gain", "cause", "weight", "gain", "could", "simply", "lack", "exercise", "excess", "calories", "diet", "easy", "cases", "solve", "simple", "diet", "exercise", "log", "need", "correct", "poor", "diet", "improper", "exercise", "cause", "weight", "gain", "could", "something", "hidden", "deep", "metabolism-something", "preventing", "losing", "weight", "matter", "hard", "try", "often", "harder", "try", "weight", "gain"], "5": ["medications", "used", "digestive", "conditions", "may", "make", "difficult", "lose", "weight", "cause", "someone", "gain", "weight", "include", "ssris", "tricyclic", "antidepressant", "medications", "amitriptyline", "nortriptyline", "desipramine", "used", "irritable", "bowel", "syndrome", "hormones", "used", "endometriosis", "digestive", "conditions", "crohn's", "disease", "ulcerative", "colitis", "often", "treated", "steroids", "steroid", "use", "cause", "weight", "gain", "also", "patients", "gerd", "gastroesophageal", "reflux", "disease", "pud", "peptic", "ulcer", "disease", "often", "feel", "better", "food", "stomach", "soak", "excess", "acid"], "6": ["cases", "though", "rapid", "abdominal", "weight", "gain", "actually", "sign", "underlying", "medical", "condition", "hormonal", "disorders", "culprits", "conditions", "including", "liver", "disease", "ovarian", "tumors", "may", "cause", "abdominal", "bloating", "weight", "gain", "well", "3d", "rendering", "human", "liver", "photo", "credit", "satellitesixty", "istock", "getty", "images", "end-stage", "liver", "disease", "liver", "failure", "also", "cause", "rapid", "abdominal", "weight", "gain", "liver", "failure", "may", "due", "number", "conditions", "including", "hepatitis", "alcohol", "abuse", "liver", "function", "deteriorates", "fluid", "called", "ascites", "accumulates", "belly"], "7": ["symptoms", "common", "usually", "matter", "concern", "constipation", "constipation", "condition", "one", "pass", "stools", "regularly", "difficulty", "passing", "stools", "due", "hard", "nature", "pain", "stomach", "bloating", "nausea", "weight", "gain", "cramps", "etc", "symptoms", "constipation", "causes", "lot", "discomfort", "also", "makes", "person", "irritable", "common", "symptom", "conditions", "like", "irritable", "bowel", "syndrome", "constipation", "etc", "however", "bloated", "stomach", "weight", "gain", "together", "rare", "symptom", "observed", "case", "certain", "health", "conditions"]}