{"0": ["moon's", "elongation", "h", "sun-h", "moon", "formula", "used", "find", "moon's", "elongation", "angular", "distance", "sun", "even", "night", "cannot", "see", "sun", "possible", "know", "sun", "know", "time", "day", "midnight", "example", "sun", "side", "earth", "h", "\u00b0", "view", "note", "moon's", "elongation", "angle", "sun", "moon", "difference", "two", "hour", "angles", "get", "negative", "number", "add", "degrees"], "1": ["moon's", "elongation", "angular", "distance", "east", "sun", "time", "new", "moon", "zero", "moon", "said", "conjunction", "full", "moon", "elongation", "\u00b0", "said", "opposition", "cases", "moon", "syzygy", "sun", "moon", "earth", "nearly", "aligned", "elongation", "either", "\u00b0", "\u00b0", "moon", "said", "quadrature", "mean", "orbital", "velocity", "1.023", "km", "moon", "moves", "relative", "stars", "hour", "amount", "roughly", "equal", "angular", "diameter", "0.5", "\u00b0", "moon", "differs", "satellites", "planets", "orbit", "close", "plane", "ecliptic", "earth's", "equatorial", "plane"], "2": ["glossary", "entry", "elongation", "moon", "apparent", "angular", "distance", "center", "moon", "center", "sun", "seen", "particular", "observer", "jimmosher", "page", "edited", "times", "last", "modification", "made", "by-jimmosher", "nov", "12:20", "pm-mgx", "elongation", "angle", "listed", "sun-observer-target", "sot", "angle", "lunar", "output", "jpl", "horizons", "approximate", "determinant", "theoretical", "percent", "illumination", "moon", "calculated", "moon", "perfect", "sphere", "see", "phase", "jimmosher"], "3": ["elongation", "angle", "sun", "planet", "seen", "observer", "earth", "imagine", "could", "see", "venus", "sun", "time", "measure", "elongation", "venus", "could", "hold", "piece", "paper", "flat", "edge", "line", "two", "objects", "planet", "opposite", "point", "sky", "sun", "elongation", "\u00b0", "however", "planets", "never", "elongation", "see", "need", "consider", "difference", "inferior", "planets", "superior", "planets"], "4": ["first", "quarter", "degrees", "eastern", "elongation", "angle", "line", "sight", "sun", "moon", "degrees", "east", "last", "quarter", "moon", "degrees", "west", "sun", "sky", "degrees", "western", "elongation", "source", "):", "rich", "\u00b7", "years", "ago", "think", "means", "distance", "moon", "sun", "degrees", "means", "respect", "mercury", "venus", "would", "\u00b0", "new", "moon", "\u00b0", "east", "first", "quarter", "\u00b0", "full", "moon", "\u00b0", "west", "third", "quarter"], "5": ["fig", "elongation", "angle", "angle", "planet", "sun", "seen", "earth", "make", "good", "model", "solar", "system", "required", "good", "observations", "good", "observations", "require", "good", "way", "talk", "planets", "referred", "position", "two", "ways", "angle", "sun", "planet", "called", "elongation", "venus", "mercury", "always", "seen", "near", "sun", "either", "right", "sunrise", "right", "sunset", "indeed", "took", "awhile", "ancient", "greeks", "realize", "morning", "evening", "stars", "planet"], "6": ["best", "answer", "elongation", "measure", "moon's", "position", "sky", "respect", "angle", "sun", "observer's", "perspective", "three-and-a-half", "day", "old", "moon", "would", "degrees", "eastern", "elongation", "think", "means", "distance", "moon", "sun", "degrees", "means", "respect", "mercury", "venus", "would", "\u00b0", "new", "moon", "\u00b0", "east", "first", "quarter", "\u00b0", "full", "moon", "\u00b0", "west", "third", "quarter"], "7": ["see", "also", "earth", "time", "clock", "animated", "visualization", "earth's", "rotation", "close", "x", "moon", "tonight", "moon", "ver", "0.1", "visualizes", "today's", "tonight's", "simulated", "moon's", "phase", "viewed", "northern", "hemisphere", "position", "moon", "relation", "earth", "sun", "north", "pole", "additionally", "displays", "lunar", "astronomical", "parameters"]}