{"0": ["receptor", "physiological", "term", "part", "nerve", "receives", "reads", "chemical", "signals", "neurotransmitters", "nerves", "transmit", "electrical", "signals", "transfer", "information", "brain", "nervous", "system"], "1": ["receptor-an", "organ", "nerve", "endings", "skin", "viscera", "eye", "ear", "nose", "mouth", "respond", "stimulation", "sense", "organ", "sensory", "receptor", "lateral", "line", "lateral", "line", "organ-sense", "organs", "fish", "amphibians", "believed", "detect", "pressure", "changes", "water", "\u00b7", "cep", "\u00b7", "tor", "nerve", "ending", "specialized", "sense", "receive", "stimuli", "skin", "receptors", "respond", "stimuli", "touch", "pressure", "signal", "brain", "activating", "portions", "nervous", "system", "receptors", "nose", "detect", "odors", "cell", "structure", "site", "capable", "combining", "hormone", "antigen", "chemical", "substance"], "2": ["receptor", "cell", "biology", "structure", "surface", "cell", "inside", "cell", "selectively", "receives", "binds", "specific", "substance", "many", "receptors", "receptor", "insulin", "receptor", "low-density", "lipoproteins", "ldl", ");", "etc", "take", "example", "receptor", "substance", "p", "molecule", "acts", "messenger", "sensation", "pain", "unique", "harbor", "cell", "surface", "substance", "p", "docks", "without", "receptor", "substance", "p", "cannot", "dock", "cannot", "deliver", "message", "pain"], "3": ["neuroanatomical", "distribution", "receptors", "three", "potential", "inhibitory", "neurotransmitters", "brainstem", "auditory", "nuclei", "cat", "glendenning", "kk", "baker", "bn", "department", "psychology", "florida", "state", "university", "tallahassee", "results", "show", "glycine", "may", "major", "inhibitory", "neurotransmitter", "auditory", "system", "ascends", "midbrain", "relatively", "high", "levels", "strychnine", "binding", "present", "every", "major", "nucleus", "system"], "4": ["cell", "system", "responsible", "stimulus", "transfer", "types", "cells", "specialists", "detecting", "responding", "stimuli", "external", "elements", "sense", "organ", "like", "eye", "ear"], "5": ["order", "visualize", "relative", "abundance", "three", "potentially", "inhibitory", "neurotransmitters", "nuclei", "brainstem", "auditory", "pathway", "receptor", "sites", "glycine", "gaba-a", "muscarinic", "acetylcholine", "ach", "localized", "cat's", "brainstem", "auditory", "system", "results", "show", "glycine", "may", "major", "inhibitory", "neurotransmitter", "auditory", "system", "ascends", "midbrain", "relatively", "high", "levels", "strychnine", "binding", "present", "every", "major", "nucleus", "system"], "6": ["cutaneous", "receptors", "types", "sensory", "receptor", "found", "dermis", "epidermis", "part", "somatosensory", "system", "cutaneous", "receptors", "include", "e", "g", "cutaneous", "mechanoreceptors", "nociceptors", "pain", "thermoreceptors", "temperature"], "7": ["sensory", "receptor", "living", "cell", "responds", "particular", "type", "energy", "receptors", "often", "housed", "sense", "organ", "specialized", "structure", "constructed", "way", "collects", "one", "type", "energy", "particularly", "well", "receptor", "cells", "respond", "finally", "magnetoreceptors", "respond", "magnetic", "fields", "magnetoreceptors", "found", "species", "honeybees", "mollusks", "hornets", "salmon", "tuna", "turtles", "salamanders", "homing", "pigeons", "receptors", "magnetoreception", "contain", "magnetite", "mineral", "magnetic", "therefore"], "8": ["sensory", "receptors", "specialized", "neurons", "nerve", "endings", "respond", "changes", "environment", "converting", "energy", "specific", "stimulus", "action", "potential", "process", "known", "transduction"]}