{"0": ["owner's", "engineer", "engineer", "represents", "owner", "project", "design", "development", "construction", "confirm", "work", "done", "well", "within", "legal", "standards", "owner's", "engineer", "inspects", "design", "plans", "timelines", "materials", "developed", "support", "project"], "1": ["basic", "definition", "owner", "engineer", "someone", "commonly", "team", "experts", "serves", "independent", "advocate", "owner", "owner", "engineer", "plays", "supporting", "critical", "role", "filling", "gaps", "supplementing", "plant", "owner", "resources", "figure"], "2": ["thatis", "retaining", "owner", "engineer", "provide", "services", "behalf", "anowner", "enhance", "definition", "management", "capital", "projects", "theoutcome", "epc", "contracts", "way", "bottom-line"], "3": ["owner", "engineer", "involved", "outset", "help", "develop", "project", "execution", "plan", "contracting", "strategy", "owner", "benefits", "partner", "intimately", "familiar", "aspects", "project", "work", "progresses"], "4": ["scope", "owner", "engineer", "vary", "depending", "upon", "specific", "requirements", "project", "owner", "ability", "execute", "various", "tasks", "initially", "owner", "engineering", "include", "process", "guidance", "development", "technology", "evaluation"], "5": ["owner", "engineer", "participate", "project", "definition", "provide", "process", "assessment", "least", "owner", "engineering", "entail", "feasibility", "study", "preliminary", "engineering", "detailed", "scope", "estimate"], "6": ["owner", "engineer", "also", "helpful", "securing", "project", "financing", "get", "best", "possible", "financing", "deal", "project", "must", "clearly", "define", "\u2014", "early", "stage", "\u2014", "schedule", "projected", "costs", "suitability", "technology", "location"], "7": ["typically", "entire", "engineering", "firm", "rather", "individual", "engineer", "provides", "service", "owner's", "engineers", "include", "team", "people", "different", "engineering", "specialties", "well", "support", "staff", "start", "work", "project", "early", "possible", "usually", "design", "development", "phase"], "8": ["owner", "engineer", "help", "take", "project", "concept", "commissioning", "especially", "important", "personnel", "cutbacks", "inexperience", "make", "hard", "owner", "manage", "intricacies", "details", "project", "in-house", "staff"]}