{"0": ["simplest", "form", "symbol", "hamsa", "hand", "talismanic", "symbol", "believed", "would", "protect", "harm", "evil", "forces", "bring", "goodness", "abundance", "fertility", "luck", "good", "health", "hamsa", "icon", "used", "man", "defence", "struggle", "forces", "evil"], "1": ["hamsa", "hand", "fatima", "added", "years", "ago", "linda", "heaphy", "hamsa", "also", "known", "humes", "hand", "hand", "fatima", "hand", "miriam", "popular", "symbol", "found", "throughout", "middle", "east", "northern", "africa", "particularly", "within", "islamic", "jewish", "faiths", "one", "national", "symbols", "algeria", "appears", "emblem"], "2": ["hamsa", "hand", "ancient", "middle", "eastern", "amulet", "symbolizing", "hand", "god", "faiths", "protective", "sign", "brings", "owner", "happiness", "luck", "health", "good", "fortune", "hamsa", "hand", "wide", "variety", "different", "spellings", "includes", "hamesh", "hamsa", "chamsa", "khamsa", "also", "identified", "hand", "miriam", "aaron", "moses", "sister", "hand", "fatima", "hamsa", "hand", "two", "main", "styles"], "3": ["hamsa", "hand", "tattoo", "meaning", "\u2013", "might", "know", "hamsa", "word", "means", "five", "means", "five", "fingers", "hand", "hand", "five", "senses", "people", "comes", "hebrew", "language", "middle", "east", "hamsa", "hands", "popular", "amulets", "among", "people"], "4": ["jewish", "culture", "hamsa", "called", "hand", "miriam", "muslim", "culture", "hand", "fatima", "fatima", "amulet", "called", "khamsa", "muslim", "world", "arabic", "word", "five", "seen", "protection", "evil", "eye", "amulet", "consists", "five", "spread", "fingers", "often", "eye", "hand"], "5": ["hamsa", "hand", "sometimes", "includes", "eye", "symbol", "thought", "protect", "evil", "eye", "often", "worn", "pendant", "necklace", "also", "found", "key", "chains", "house", "decorations", "baby", "carriages", "jewelry", "items", "hamsa", "hand", "wide", "variety", "different", "spellings", "includes", "hamesh", "hamsa", "chamsa", "khamsa", "also", "identified", "hand", "miriam", "aaron", "moses", "sister", "hand", "fatima", "hamsa", "hand", "two", "main", "styles"], "6": ["name", "hamsa", "comes", "hebrew", "word", "hamesh", "means", "five", "hamsa", "refers", "fact", "five", "fingers", "talisman", "though", "also", "believe", "represents", "five", "books", "torah", "sometimes", "called", "hand", "miriam", "moses", "sister", "ariela", "pelaia", "hamsa", "amulet", "shaped", "like", "hand", "three", "extended", "fingers", "middle", "curved", "thumb", "pinky", "finger", "either", "side", "thought", "protect", "evil", "eye", "popular", "motif", "jewish", "middle", "eastern", "jewelry"], "7": ["simplest", "form", "symbol", "hamsa", "hand", "talismanic", "symbol", "believed", "would", "protect", "harm", "evil", "forces", "bring", "goodness", "abundance", "fertility", "luck", "good", "health", "hamsa", "icon", "used", "man", "defence", "struggle", "forces", "evil", "hamsa", "number", "five", "arabs", "call", "icon", "khamse", "hand"], "8": ["hamsa", "hand", "hand", "fatima", "become", "popular", "good", "luck", "symbols", "worldwide", "common", "symbols", "jewish", "muslim", "communities", "jewish", "communities", "called", "hamsa", "hand", "hand", "miriam", "muslim", "communities", "called", "hand", "fatima", "khamsa", "hamsa", "hebrew", "word", "five", "likewise", "khamsa", "arabic", "word", "five", "hamsa", "hand", "hand", "fatima", "equally", "best", "known", "power", "protect", "owner", "evil", "eye", "bring", "happiness", "holder"]}