{"0": ["mm", "left", "uvj", "stone", "year", "started", "several", "acute", "extremely", "painful", "colics", "since", "symptoms", "became", "muted", "diagnosed", "started", "flomax", "dramatically", "increased", "fluid", "intake", "symptoms", "rest", "last", "summer"], "1": ["definitions", "abbreviation", "ureterovesical", "junction", "definition", "information", "uvj", "provided", "stedman's", "search", "medical", "dictionary", "stedman's", "part", "lippincott", "williams", "wilkins", "provides", "comprehensive", "line", "health-science", "publications", "healthcare", "professionals", "medical", "students"], "2": ["ureterovesical", "junction", "uvj", "site", "entry", "ureter", "bladder", "oblique", "angulation", "detrusor", "avoid", "reflux", "pertaining", "ureter", "bladder", "ureterovesical", "junction", "junction", "ureter", "urinary", "bladder", "ureter", "runs", "short", "distance", "wall", "bladder", "providing", "valvular", "action", "preventing", "reflux", "urine", "ureter"], "3": ["world's", "comprehensive", "professionally", "edited", "abbreviations", "acronyms", "database", "trademarks", "service", "marks", "referenced", "site", "properties", "respective", "owners", "acronym", "finder", "\u00a9", "1988-2015", "acronym", "finder", "rights", "reserved"], "4": ["ureterovesical", "pertaining", "ureter", "bladder", "ureterovesical", "junction", "junction", "ureter", "urinary", "bladder", "ureter", "runs", "short", "distance", "wall", "bladder", "providing", "valvular", "action", "preventing", "reflux", "urine", "ureter"], "5": ["forums", "message", "boards", "ask", "answer", "question", "boards", "cannot", "get", "diagnosis", "tell", "us", "medical", "story", "share", "misdiagnosis", "story", "best", "treatment", "condition", "see", "boards"], "6": ["ultrasound", "usually", "unilateral", "rarely", "bilateral", "hydronephrosis", "dilated", "ureter", "seen", "serpiginous", "anechoic", "cystic", "structure", "abdomen", "retrovesical", "space", "ureter", "retroperitoneal", "therefore", "appears", "fluid-filled", "structure", "adjacent", "fetal", "spine", "dilated"], "7": ["welcome", "site", "una", "voce", "japan", "una", "voce", "japan", "uvj", "aims", "safeguarding", "rich", "liturgical", "heritage", "catholic", "church", "promoting", "use", "sacramental", "life", "church", "j", "apan", "full", "obedience", "magisterium", "church", "local", "ordinaries"], "8": ["ureterovesical", "junction", "uvj", "obstruction", "refers", "blockage", "area", "obstruction", "impedes", "flow", "urine", "bladder", "causing", "urine", "back", "dilate", "ureters", "kidney", "megaureter", "hydronephrosis", "unilateral", "uvj", "obstruction", "second", "common", "prenatally", "detected", "obstructive", "disease", "often", "picked", "maternal", "ultrasounds", "pregnancy"], "9": ["effect", "renal", "pelvic", "distension", "ureteropelvic", "ureterovesical", "junctions", "urinary", "bladder", "renal", "pelvivesical", "reflex", "shafik", "author", "information", "department", "surgery", "experimental", "research", "faculty", "medicine", "cairo", "university", "egypt"]}