{"0": ["amboy", "census", "designated", "place", "population", "1,631", "july", "amboy", "ranks", "lower", "quartile", "population", "density", "diversity", "index", "compared", "cities", "towns", "census", "designated", "places", "cdps", "washington", "table", "compares", "amboy", "incorporated", "cities", "towns", "cdps", "washington", "rank", "percentile", "using", "july", "data", "location", "ranked", "highest", "value", "location", "ranks", "higher", "peers", "would", "75th", "percentile", "peer", "group"], "1": ["formal", "boundaries", "amboy", "census", "designated", "place", "see", "map", "encompass", "land", "area", "9.99", "sq", "miles", "water", "area", "0.02", "sq", "miles", "clark", "county", "pacific", "time", "zone", "gmt", "8)", "elevation", "feet", "table", "compares", "amboy", "incorporated", "cities", "towns", "cdps", "washington", "rank", "percentile", "using", "july", "data", "location", "ranked", "highest", "value", "location", "ranks", "higher", "peers", "would", "75th", "percentile", "peer", "group"], "2": ["amboy", "located", "northern", "clark", "county", "\u00b0", "\u2032", "\u2033", "n", "\u00b0", "\u2032", "\u2033", "w", "\ufeff", "\ufeff", "45.90333", "\u00b0", "n", "122.4655", "\u00b0", "w", "\ufeff", "45.90333", "-122.46556", "45.903228", "-122.465678", "junction", "chelatchie", "creek", "cedar", "creek", "west-flowing", "tributary", "lewis", "river", "according", "united", "states", "census", "bureau", "amboy", "cdp", "total", "area", "10.0", "square", "miles", "25.9", "km", "0.02", "square", "miles", "0.04", "km", "0.16", "water", "reduction", "total", "area", "14.3", "square", "miles", "37.1", "km", "census"], "3": ["amboy", "wa", "sales", "tax", "rate", "current", "total", "local", "sales", "tax", "rate", "amboy", "wa", "7.700", "december", "total", "local", "sales", "tax", "rate", "also", "7.700", "amboy", "wa", "clark", "county", "amboy", "following", "zip", "codes"], "4": ["local", "citizens", "artisans", "businesses", "organizations", "north", "clark", "county", "area", "developing", "museum", "located", "amboy", "adjoining", "territorial", "community", "park", "former", "church", "building", "dedicated", "process", "renovation", "house", "native", "american", "pioneer", "logging", "exhibits"], "5": ["landwatch.com", "thousands", "rural", "properties", "amboy", "clark", "county", "washington", "including", "hunting", "fishing", "properties", "cabins", "land", "sale", "land", "auctions", "choose", "small", "acreage", "lots", "massive", "acre", "estates", "2.5", "acres", "amboy", "clark", "county", "washington", "65,000", "private", "2.5", "acre", "building", "lot", "quiet", "wooded", "subdivision", "near", "chelatchie", "prairie", "store"], "6": ["amboy", "unincorporated", "community", "census-designated", "place", "cdp", "clark", "county", "washington", "united", "states", "population", "1,608", "census", "2,085", "census", "according", "united", "states", "census", "bureau", "amboy", "cdp", "total", "area", "10.0", "square", "miles", "25.9", "km", "0.02", "square", "miles", "0.04", "km", "0.16", "water", "reduction", "total", "area", "14.3", "square", "miles", "37.1", "km"], "7": ["district", "comprised", "mt", "view", "cemetery", "amboy", "cemetery", "chelatchie", "cemeteries", "amboy", "wa", "believe", "cemeteries", "comfort", "living", "well", "place", "honor", "dead"], "8": ["amboy", "washington", "quiet", "rural", "setting", "miles", "north", "battle", "ground", "washington", "beautiful", "section", "clark", "county", "seeking", "conveniences", "densely", "populated", "areas", "clark", "county", "amboy", "offers", "peaceful", "solitude", "puts", "one", "bit", "closer", "nature", "slower", "pace", "life"]}