{"0": ["optimum", "conditions", "temperature", "humidity", "chicken", "egg", "takes", "days", "hatch", "layed", "20-28", "days", "depending", "breed", "th", "\u2026", "e", "time", "egg", "first", "cracked", "one", "day", "slow", "process", "hatched", "naturally", "broody", "hens", "take", "days", "gather", "enough", "eggs", "set", "nest", "next", "days", "seldom", "leave", "nest", "except", "defecating", "occasionally", "food", "water", "allow", "eggs", "drop", "degree", "two", "temperature"], "1": ["record", "day", "many", "eggs", "incubated", "calendar", "able", "estimate", "hatch", "date", "based", "average", "incubation", "times", "bird", "species", "want", "hatch", "example", "chicken", "eggs", "typically", "take", "days", "hatch", "whereas", "many", "duck", "varieties", "peafowl", "may", "take", "days", "turn", "eggs", "least", "three", "times", "daily"], "2": ["reason", "temperature", "dropped", "correct", "temperature", "occasions", "could", "find", "eggs", "hatching", "day", "even", "day", "whereas", "fertilized", "chicken", "eggs", "usually", "take", "exactly", "days", "hatch", "duck", "eggs", "take", "days", "apart", "muscovy", "ducks", "general", "rule", "thumb", "eggs", "muscovy", "ducks", "take", "days", "vary", "slightly", "depending", "conditions", "answer", "days", "exactly", "although", "need", "bear", "mind", "vary", "depending", "number", "circumstances", "generally", "speaking", "however", "fertile", "chicken", "eggs", "hatched", "hen", "take", "days", "see", "little", "faces", "staring", "underneath", "mamma's", "wings"], "3": ["chicken", "eggs", "incubation", "period", "days", "hatched", "using", "either", "specialized", "incubator", "carefully", "monitored", "conditions", "using", "broody", "hen", "use", "tips", "hatching", "chicken", "eggs", "using", "methods", "broody", "hen", "used", "incubate", "hatch", "chicken", "eggs", "even", "lay", "eggs", "great", "natural", "option", "hatching", "eggs", "make", "sure", "choose", "broody", "breed", "hatch", "eggs", "popular", "broody", "breeds", "include", "silkies", "cochins", "orpingtons", "old", "english", "games"], "4": ["long", "take", "fertilized", "chicken", "eggs", "hatch", "answer", "days", "exactly", "although", "need", "bear", "mind", "vary", "depending", "number", "circumstances", "generally", "speaking", "however", "fertile", "chicken", "eggs", "hatched", "hen", "take", "days", "see", "little", "faces", "staring", "underneath", "mamma's", "wings"], "5": ["hand", "use", "incubator", "order", "hatch", "fertilized", "chicken", "eggs", "sometimes", "hatch", "day", "two", "early", "also", "hatch", "days", "late", "things", "like", "humidity", "temperature", "play", "significant", "role", "answer", "days", "exactly", "although", "need", "bear", "mind", "vary", "depending", "number", "circumstances", "generally", "speaking", "however", "fertile", "chicken", "eggs", "hatched", "hen", "take", "days", "see", "little", "faces", "staring", "underneath", "mamma's", "wings"], "6": ["takes", "days", "hatch", "egg", "turned", "first", "days", "twice", "day", "one", "turn", "morning", "one", "night", "chickens", "hatched", "21-24", "\u2026", "ays", "though", "days", "main", "time", "hatched", "naturally", "broody", "hens", "take", "days", "gather", "enough", "eggs", "set", "nest", "next", "days", "seldom", "leave", "nest", "except", "defecating", "occasionally", "food", "water", "allow", "eggs", "drop", "degree", "two", "temperature"], "7": ["takes", "days", "average", "egg", "hatch", "incubation", "begins", "placing", "eggs", "inside", "turn", "heat", "source", "measure", "temperature", "humidity", "hour", "period", "making", "adjustments", "necessary", "create", "optimal", "environment", "temperature", "eggs", "need", "kept", "99.5", "degrees", "times", "one", "degree", "higher", "lower", "hours", "terminate", "embryo", "humidity", "percent", "humidity", "must", "maintained", "first", "days", "percent", "humidity", "needed", "final", "days", "hatching"], "8": ["day", "counted", "full", "hours", "day", "would", "first", "setting", "egg", "day", "next", "hours", "etc", "set", "eggs", "monday", "usually", "safe", "bet", "hatch", "monday", "weeks", "later", "select", "clean", "even", "shaped", "undamaged", "eggs", "incubating", "fertility", "candling", "natural", "fertility", "rarely", "may", "vary", "season", "condition", "type", "birds", "might", "safe", "expect", "fertile", "eggs", "hatch", "though", "hatches", "happen", "shipped", "eggs", "hatch", "rate", "approximately", "overall"], "9": ["chicken", "eggs", "take", "exactly", "days", "date", "started", "incubating", "hatched", "naturally", "broody", "hens", "take", "days", "gather", "enough", "eggs", "set", "nest", "next", "days", "seldom", "leave", "nest", "except", "defecating", "occasionally", "food", "water", "allow", "eggs", "drop", "degree", "two", "temperature"]}